seveno_pyutil/__init__.py
seveno_pyutil/benchmarking_utilities.py
seveno_pyutil/collections_utilities.py
seveno_pyutil/datetime_utilities.py
seveno_pyutil/error_utilities.py
seveno_pyutil/file_utilities.py
seveno_pyutil/metaprogramming_helpers.py
seveno_pyutil/os_utilities.py
seveno_pyutil/string_utilities.py
seveno_pyutil/logging_utilities/__init__.py
seveno_pyutil/logging_utilities/pretty_formatter.py
seveno_pyutil/logging_utilities/sql_filter.py
seveno_pyutil/logging_utilities/standard_metadata_filter.py
seveno_pyutil/logging_utilities/utilities.py
seveno_pyutil-0.9.2.dist-info/LICENSE
seveno_pyutil-0.9.2.dist-info/METADATA
seveno_pyutil-0.9.2.dist-info/WHEEL
seveno_pyutil-0.9.2.dist-info/top_level.txt
seveno_pyutil-0.9.2.dist-info/RECORD
