Metadata-Version: 2.2
Name: seveno-pyutil
Version: 0.9.2
Summary: Various unsorted Python utilities
Author-email: Tomislav Adamic <tomislav.adamic@gmail.com>
License: MIT
Project-URL: Source, https://github.com/tadams42/seveno_pyutil
Project-URL: Documentation, https://seveno-pyutil.readthedocs.io/en/latest/
Keywords: utilities
Platform: any
Classifier: Development Status :: 4 - Beta
Classifier: Intended Audience :: Developers
Classifier: License :: OSI Approved :: MIT License
Classifier: Programming Language :: Python
Classifier: Programming Language :: Python :: 3
Classifier: Programming Language :: Python :: 3.10
Classifier: Programming Language :: Python :: 3.11
Classifier: Programming Language :: Python :: 3.12
Classifier: Programming Language :: Python :: 3.13
Classifier: Programming Language :: Python :: 3 :: Only
Classifier: Operating System :: OS Independent
Classifier: Topic :: Software Development :: Libraries :: Python Modules
Requires-Python: >=3.10
License-File: LICENSE
Requires-Dist: colorlog
Requires-Dist: holidays
Requires-Dist: pretty-traceback
Requires-Dist: pygments
Requires-Dist: python-dateutil>=2.6.0
Requires-Dist: sqlglot[rs]
Requires-Dist: tzlocal
Provides-Extra: dev
Requires-Dist: black; extra == "dev"
Requires-Dist: bump2version; extra == "dev"
Requires-Dist: ipython; extra == "dev"
Requires-Dist: rich; extra == "dev"
Requires-Dist: pre-commit; extra == "dev"
Requires-Dist: ruff; extra == "dev"
Provides-Extra: docs
Requires-Dist: furo; extra == "docs"
Requires-Dist: myst-parser; extra == "docs"
Requires-Dist: sphinx; extra == "docs"
Requires-Dist: sphinx-copybutton; extra == "docs"
Provides-Extra: tests
Requires-Dist: check-manifest; extra == "tests"
Requires-Dist: pytest; extra == "tests"
Requires-Dist: coverage; extra == "tests"
Requires-Dist: factory-boy; extra == "tests"
Requires-Dist: faker; extra == "tests"
Requires-Dist: pytest-spec; extra == "tests"
